{"fit1nll":6768.7208,"fit1xnorm":26.7135,"fit1gnorm":22.8028,"fit1mae_cases":820.3183,"fit1mae_hosps":42.7764,"fit1mae_death":16.4474,"fit1mase_cases":0.962,"fit1mase_hosps":1.3327,"fit1mase_death":0.8802,"fit1iter":100,"fit1walltime":1674.064,"fit1hessposdef":true,"fit1convergence":-997,"fit2nll":6768.3262,"fit2xnorm":26.7059,"fit2gnorm":71.7427,"fit2mae_cases":814.248,"fit2mae_hosps":42.7535,"fit2mae_death":16.4008,"fit2mase_cases":0.9549,"fit2mase_hosps":1.332,"fit2mase_death":0.8777,"fit2iter":10,"fit2hessposdef":true,"fit2walltime":293.405,"fit2convergence":-997,"delta":-0.0395}
